{
  "NOTICE": "Not public API, DO NOT use this file",
  "release_pages": [
    {
      "index": 1,
      "etag": "\"71226532b958b5c28a7e2b752a92d14f24967421c5219c3eaf2ba798536ea541\"",
      "release_tags": [
        "v1.2.2",
        "v1.2.1",
        "v1.2.0",
        "v1.1.2",
        "v1.1.1"
      ],
      "empty": false
    },
    {
      "index": 2,
      "etag": "\"1db6a3a21548bf6e068a9a9337e4151e9d1135718e089e7e62dc0509406337bf\"",
      "release_tags": [],
      "empty": true
    }
  ]
}