{
  "NOTICE": "Not public API, DO NOT use this file",
  "release_pages": [
    {
      "index": 1,
      "etag": "\"35e65394bcc4f861cf493068fc9b7d2d36d3b77997e0465f177e143dfcad07d5\"",
      "release_tags": [
        "v1.2.2",
        "v1.2.1",
        "v1.2.0",
        "v1.1.2",
        "v1.1.1"
      ],
      "empty": false
    },
    {
      "index": 2,
      "etag": "\"1db6a3a21548bf6e068a9a9337e4151e9d1135718e089e7e62dc0509406337bf\"",
      "release_tags": [],
      "empty": true
    }
  ]
}