{
  "NOTICE": "Not public API, DO NOT use this file",
  "release_pages": [
    {
      "index": 1,
      "etag": "\"3a143fcb64985154ded0873d9deebf4a99dc4fb6cba22d4eb3b64474df3f2df7\"",
      "release_tags": [
        "qq_api-v1.2.0",
        "qq_api-v1.1.1",
        "qq_api-v1.1.0",
        "qq_api-v1.0.0"
      ],
      "empty": false
    },
    {
      "index": 2,
      "etag": "\"1db6a3a21548bf6e068a9a9337e4151e9d1135718e089e7e62dc0509406337bf\"",
      "release_tags": [],
      "empty": true
    }
  ]
}