{
  "NOTICE": "Not public API, DO NOT use this file",
  "release_pages": [
    {
      "index": 1,
      "etag": "\"86584ef3a5fbf7fd36d0e87e59f7d25f91fe65c07adb09f0ae8708a37e1aa552\"",
      "release_tags": [
        "qq_api-v1.2.0",
        "qq_api-v1.1.1",
        "qq_api-v1.1.0",
        "qq_api-v1.0.0"
      ],
      "empty": false
    },
    {
      "index": 2,
      "etag": "\"1db6a3a21548bf6e068a9a9337e4151e9d1135718e089e7e62dc0509406337bf\"",
      "release_tags": [],
      "empty": true
    }
  ]
}